CHANGELOG.rst
CONTRIBUTING.rst
LICENSE.txt
MANIFEST.in
README.rst
requirements.txt
setup.cfg
setup.py
tests.py
pyzipcode/__init__.py
pyzipcode/pyzipcode.py
pyzipcode_cli.egg-info/PKG-INFO
pyzipcode_cli.egg-info/SOURCES.txt
pyzipcode_cli.egg-info/dependency_links.txt
pyzipcode_cli.egg-info/requires.txt
pyzipcode_cli.egg-info/top_level.txt