Metadata-Version: 1.1
Name: pyzipcode-cli
Version: 0.1.4
Summary: a thin wrapper around getziptastic's API v2
Home-page: https://github.com/prodicus/pyzipcode-cli
Author: Tasdik Rahman
Author-email: tasdik95@gmail.com
License: MIT
Download-URL: https://github.com/prodicus/pyzipcode-cli/tarball/0.1.4
Keywords: api,geo-location,zipcode,devtools,Development,ziptastic,latitude,longitude
Platform: UNKNOWN
Classifier: Intended Audience :: Developers
Classifier: Topic :: Software Development :: Build Tools
Classifier: License :: OSI Approved :: MIT License
Classifier: Programming Language :: Python :: 2.7
Classifier: Programming Language :: Python :: 3
Classifier: Programming Language :: Python :: 3.4
